ins_pricing/README.md
ins_pricing/__init__.py
ins_pricing/setup.py
ins_pricing/cli/BayesOpt_entry.py
ins_pricing/cli/BayesOpt_incremental.py
ins_pricing/cli/Explain_Run.py
ins_pricing/cli/Explain_entry.py
ins_pricing/cli/Pricing_Run.py
ins_pricing/cli/__init__.py
ins_pricing/cli/bayesopt_entry_runner.py
ins_pricing/cli/watchdog_run.py
ins_pricing/cli/utils/__init__.py
ins_pricing/cli/utils/cli_common.py
ins_pricing/cli/utils/cli_config.py
ins_pricing/cli/utils/notebook_utils.py
ins_pricing/cli/utils/run_logging.py
ins_pricing/docs/modelling/BayesOpt_USAGE.md
ins_pricing/docs/modelling/README.md
ins_pricing/governance/README.md
ins_pricing/governance/__init__.py
ins_pricing/governance/approval.py
ins_pricing/governance/audit.py
ins_pricing/governance/registry.py
ins_pricing/governance/release.py
ins_pricing/modelling/__init__.py
ins_pricing/modelling/core/BayesOpt.py
ins_pricing/modelling/core/__init__.py
ins_pricing/modelling/core/evaluation.py
ins_pricing/modelling/core/bayesopt/__init__.py
ins_pricing/modelling/core/bayesopt/config_preprocess.py
ins_pricing/modelling/core/bayesopt/core.py
ins_pricing/modelling/core/bayesopt/model_explain_mixin.py
ins_pricing/modelling/core/bayesopt/model_plotting_mixin.py
ins_pricing/modelling/core/bayesopt/utils.py
ins_pricing/modelling/core/bayesopt/models/__init__.py
ins_pricing/modelling/core/bayesopt/models/model_ft_components.py
ins_pricing/modelling/core/bayesopt/models/model_ft_trainer.py
ins_pricing/modelling/core/bayesopt/models/model_gnn.py
ins_pricing/modelling/core/bayesopt/models/model_resn.py
ins_pricing/modelling/core/bayesopt/trainers/__init__.py
ins_pricing/modelling/core/bayesopt/trainers/trainer_base.py
ins_pricing/modelling/core/bayesopt/trainers/trainer_ft.py
ins_pricing/modelling/core/bayesopt/trainers/trainer_glm.py
ins_pricing/modelling/core/bayesopt/trainers/trainer_gnn.py
ins_pricing/modelling/core/bayesopt/trainers/trainer_resn.py
ins_pricing/modelling/core/bayesopt/trainers/trainer_xgb.py
ins_pricing-0.2.1.dist-info/METADATA
ins_pricing-0.2.1.dist-info/WHEEL
ins_pricing-0.2.1.dist-info/top_level.txt
ins_pricing-0.2.1.dist-info/RECORD
