Metadata-Version: 2.4
Name: ins_pricing
Version: 0.2.1
Summary: Reusable modelling, pricing, governance, and reporting utilities.
Author: meishi125478
License: Proprietary
Keywords: pricing,insurance,bayesopt,ml
Classifier: Programming Language :: Python :: 3
Classifier: Programming Language :: Python :: 3 :: Only
Classifier: Programming Language :: Python :: 3.9
Classifier: License :: Other/Proprietary License
Classifier: Operating System :: OS Independent
Classifier: Intended Audience :: Developers
Requires-Python: >=3.9
Requires-Dist: numpy>=1.20
Requires-Dist: pandas>=1.4
Provides-Extra: bayesopt
Requires-Dist: torch>=1.13; extra == "bayesopt"
Requires-Dist: optuna>=3.0; extra == "bayesopt"
Requires-Dist: xgboost>=1.6; extra == "bayesopt"
Requires-Dist: scikit-learn>=1.1; extra == "bayesopt"
Requires-Dist: statsmodels>=0.13; extra == "bayesopt"
Requires-Dist: joblib>=1.2; extra == "bayesopt"
Requires-Dist: matplotlib>=3.5; extra == "bayesopt"
Provides-Extra: plotting
Requires-Dist: matplotlib>=3.5; extra == "plotting"
Requires-Dist: scikit-learn>=1.1; extra == "plotting"
Provides-Extra: explain
Requires-Dist: torch>=1.13; extra == "explain"
Requires-Dist: shap>=0.41; extra == "explain"
Requires-Dist: scikit-learn>=1.1; extra == "explain"
Provides-Extra: geo
Requires-Dist: contextily>=1.3; extra == "geo"
Requires-Dist: matplotlib>=3.5; extra == "geo"
Provides-Extra: gnn
Requires-Dist: torch>=1.13; extra == "gnn"
Requires-Dist: pynndescent>=0.5; extra == "gnn"
Requires-Dist: torch-geometric>=2.3; extra == "gnn"
Provides-Extra: all
Requires-Dist: torch>=1.13; extra == "all"
Requires-Dist: optuna>=3.0; extra == "all"
Requires-Dist: xgboost>=1.6; extra == "all"
Requires-Dist: scikit-learn>=1.1; extra == "all"
Requires-Dist: statsmodels>=0.13; extra == "all"
Requires-Dist: joblib>=1.2; extra == "all"
Requires-Dist: matplotlib>=3.5; extra == "all"
Requires-Dist: shap>=0.41; extra == "all"
Requires-Dist: contextily>=1.3; extra == "all"
Requires-Dist: pynndescent>=0.5; extra == "all"
Requires-Dist: torch-geometric>=2.3; extra == "all"
